setup.py
curve/__init__.py
curve/curve.py
curve_tools.egg-info/PKG-INFO
curve_tools.egg-info/SOURCES.txt
curve_tools.egg-info/dependency_links.txt
curve_tools.egg-info/top_level.txt