Metadata-Version: 2.1
Name: curve-tools
Version: 1.0
Summary: Tool set to analyze curve
Home-page: 
Author: felix
Author-email: qiyu_sjtu@163.com
License: UNKNOWN
Platform: UNKNOWN
